technews/__init__.py
technews/daily_news.py
technews/mail_helper.py
technews/mail_util.py
technews/technews_helper.py
technews/crawlers/__init__.py
technews/crawlers/business_next.py
technews/crawlers/inside.py
technews/crawlers/ithome.py
technews_tw-1.3.5.dist-info/LICENSE.txt
technews_tw-1.3.5.dist-info/METADATA
technews_tw-1.3.5.dist-info/WHEEL
technews_tw-1.3.5.dist-info/top_level.txt
technews_tw-1.3.5.dist-info/RECORD
