Metadata-Version: 2.1
Name: technews-tw
Version: 1.3.5
Summary: Taiwan tech news crawlers.
Home-page: https://github.com/WisChang005/technews_tw
Author: Wis Chang
Author-email: wistw.chang@gmail.com
Classifier: Programming Language :: Python :: 3
Classifier: License :: OSI Approved :: MIT License
Classifier: Operating System :: OS Independent
Requires-Python: >=3.6
License-File: LICENSE.txt
Requires-Dist: bs4
Requires-Dist: requests
Requires-Dist: html5lib
Requires-Dist: lxml
Requires-Dist: twine
Requires-Dist: wheel
Requires-Dist: setuptools
